autocsv_profiler/__init__.py
autocsv_profiler/analyzer.py
autocsv_profiler/base.py
autocsv_profiler/cli.py
autocsv_profiler/constants.py
autocsv_profiler/plots.py
autocsv_profiler/py.typed
autocsv_profiler/stats.py
autocsv_profiler/summarize.py
autocsv_profiler/types.py
autocsv_profiler/version.py
autocsv_profiler/config/__init__.py
autocsv_profiler/config/settings.py
autocsv_profiler/config/viz_config.py
autocsv_profiler/core/__init__.py
autocsv_profiler/core/dataset_info.py
autocsv_profiler/core/exceptions.py
autocsv_profiler/core/logger.py
autocsv_profiler/core/utils.py
autocsv_profiler/core/validation.py
autocsv_profiler/core/warnings.py
autocsv_profiler/ui/__init__.py
autocsv_profiler/ui/components.py
autocsv_profiler/ui/interactive.py
autocsv_profiler/ui/interface.py
autocsv_profiler-2.0.0.dist-info/licenses/LICENSE
autocsv_profiler-2.0.0.dist-info/licenses/NOTICE
autocsv_profiler-2.0.0.dist-info/licenses/THIRD_PARTY_LICENSES.txt
autocsv_profiler-2.0.0.dist-info/METADATA
autocsv_profiler-2.0.0.dist-info/WHEEL
autocsv_profiler-2.0.0.dist-info/entry_points.txt
autocsv_profiler-2.0.0.dist-info/top_level.txt
autocsv_profiler-2.0.0.dist-info/RECORD
