Metadata-Version: 2.4
Name: autocsv-profiler
Version: 2.0.0
Summary: Automated CSV data analysis with statistical profiling and visualization
Author-email: dhaneshbb <dhaneshbb5@gmail.com>
Maintainer-email: dhaneshbb <dhaneshbb5@gmail.com>
License-Expression: MIT
Project-URL: Homepage, https://github.com/dhaneshbb/autocsv-profiler
Project-URL: Documentation, https://github.com/dhaneshbb/autocsv-profiler/blob/master/docs/index.md
Project-URL: Repository, https://github.com/dhaneshbb/autocsv-profiler.git
Project-URL: Issues, https://github.com/dhaneshbb/autocsv-profiler/issues
Project-URL: Changelog, https://github.com/dhaneshbb/autocsv-profiler/blob/master/CHANGELOG.md
Keywords: csv,data-analysis,profiling,statistics,pandas,data-quality,exploratory-analysis,visualization,statistical-analysis,data-profiling,automated-analysis,csv-analysis,data-exploration
Classifier: Development Status :: 4 - Beta
Classifier: Intended Audience :: Developers
Classifier: Intended Audience :: Science/Research
Classifier: Intended Audience :: Information Technology
Classifier: Operating System :: OS Independent
Classifier: Programming Language :: Python :: 3
Classifier: Programming Language :: Python :: 3.8
Classifier: Programming Language :: Python :: 3.9
Classifier: Programming Language :: Python :: 3.10
Classifier: Programming Language :: Python :: 3.11
Classifier: Programming Language :: Python :: 3.12
Classifier: Programming Language :: Python :: 3.13
Classifier: Topic :: Scientific/Engineering :: Information Analysis
Classifier: Topic :: Scientific/Engineering :: Visualization
Classifier: Topic :: Software Development :: Libraries :: Python Modules
Classifier: Topic :: Software Development :: Quality Assurance
Classifier: Topic :: Utilities
Requires-Python: >=3.8
License-File: LICENSE
License-File: NOTICE
License-File: THIRD_PARTY_LICENSES.txt
Requires-Dist: pandas==2.3.1
Requires-Dist: numpy==2.2.6
Requires-Dist: scipy>=1.10.0
Requires-Dist: researchpy>=0.3.0
Requires-Dist: statsmodels>=0.14.0
Requires-Dist: matplotlib>=3.5.0
Requires-Dist: seaborn>=0.11.0
Requires-Dist: rich==14.1.0
Requires-Dist: tqdm==4.67.1
Requires-Dist: psutil==7.0.0
Requires-Dist: charset-normalizer>=3.0.0
Requires-Dist: pyyaml==6.0.2
Requires-Dist: tabulate==0.9.0
Requires-Dist: tableone==0.9.5
Provides-Extra: dev
Requires-Dist: pytest>=8.0.0; extra == "dev"
Requires-Dist: pytest-cov>=6.0.0; extra == "dev"
Requires-Dist: pytest-xdist>=3.0.0; extra == "dev"
Requires-Dist: pytest-timeout>=2.1.0; extra == "dev"
Requires-Dist: pytest-mock>=3.10.0; extra == "dev"
Requires-Dist: mypy>=1.8.0; extra == "dev"
Requires-Dist: black>=24.0.0; extra == "dev"
Requires-Dist: flake8>=7.0.0; extra == "dev"
Requires-Dist: isort>=5.12.0; extra == "dev"
Requires-Dist: pre-commit>=3.0.0; extra == "dev"
Dynamic: license-file
